open_translation/__init__.py
open_translation/open_translation.py
open_translation-0.3.1.dist-info/LICENSE
open_translation-0.3.1.dist-info/METADATA
open_translation-0.3.1.dist-info/WHEEL
open_translation-0.3.1.dist-info/top_level.txt
open_translation-0.3.1.dist-info/RECORD
