Metadata-Version: 2.1
Name: open-translation
Version: 0.3.1
Summary: Open Translation
Home-page: https://github.com/cahya-wirawan/open_translation
Author: Cahya Wirawan
Author-email: cahya.wirawan@gmail.com
License: MIT
Classifier: License :: OSI Approved :: MIT License
Classifier: Operating System :: OS Independent
Classifier: Programming Language :: Python :: 3
Requires-Python: >=3.7
License-File: LICENSE
Requires-Dist: nltk
